xla_plugins/xla_cpu_pjrt/__init__.py
xla_cpu_pjrt-0.0.0.dev0.dist-info/WHEEL
xla_cpu_pjrt-0.0.0.dev0.dist-info/METADATA
xla_cpu_pjrt-0.0.0.dev0.dist-info/entry_points.txt
xla_cpu_pjrt-0.0.0.dev0.dist-info/RECORD
