Metadata-Version: 2.1
Name: xla_cpu_pjrt
Author: The OpenXLA Authors
Summary: XLA PJRT Plugin
Classifier: Development Status :: 1 - Planning
Version: 0.0.0.dev0
